{
  "data": {
    "claimAmountBreakupSummaryObject": "| Description | Amount | \n |---|---| \n | asasasa | £ 3000.00 |\n  | **Total** | £ 3000.00 |",
    "totalClaimAmount": "3000",
    "totalInterest": null,
    "CaseAccessCategory": null
  },
  "event": {
    "id": "CREATE_CLAIM_SPEC",
    "summary": "",
    "description": ""
  },
  "event_data": {
    "applicant1": {
      "type": "COMPANY",
      "individualTitle": null,
      "companyName": "claimant ltd",
      "soleTraderTitle": null,
      "partyEmail": null,
      "partyPhone": null,
      "partyName": "claimant ltd",
      "partyTypeDisplayValue": "Company",
      "partyID": null,
      "primaryAddress": {
        "AddressLine1": "30 Hibernia Gardens",
        "AddressLine2": "",
        "AddressLine3": "",
        "PostTown": "Hounslow",
        "County": "",
        "Country": "United Kingdom",
        "PostCode": "TW3 3SD"
      },
      "unavailableDates": [],
      "flags": {
        "roleOnCase": null,
        "partyName": null,
        "groupId": null,
        "visibility": null,
        "details": []
      }
    },
    "addApplicant2": "No",
    "applicantSolicitor1CheckEmail": {
      "email": "civil.damages.claims+organisation.1.solicitor.1@gmail.com",
      "correct": "No"
    },
    "applicantSolicitor1UserDetails": {
      "email": "civilmoneyclaimsdemo@gmail.com",
      "id": null
    },
    "applicant1OrganisationPolicy": {
      "OrgPolicyCaseAssignedRole": "[APPLICANTSOLICITORONE]",
      "OrgPolicyReference": "asasas",
      "PrepopulateToUsersOrganisation": null,
      "Organisation": {
        "OrganisationID": "7H4MGE5",
        "OrganisationName": "Civil Damages Claims - Organisation 1"
      },
      "PreviousOrganisations": []
    },
    "specApplicantCorrespondenceAddressRequired": "No",
    "respondent1": {
      "type": "COMPANY",
      "individualTitle": null,
      "companyName": "def ltd",
      "soleTraderTitle": null,
      "soleTraderTradingAs": null,
      "partyEmail": null,
      "partyPhone": null,
      "individualDateOfBirth": null,
      "soleTraderDateOfBirth": null,
      "partyName": "def ltd",
      "partyTypeDisplayValue": "Company",
      "partyID": null,
      "primaryAddress": {
        "AddressLine1": "30 Hibernia Gardens",
        "AddressLine2": "",
        "AddressLine3": "",
        "PostTown": "Hounslow",
        "County": "",
        "Country": "United Kingdom",
        "PostCode": "TW3 3SD"
      },
      "unavailableDates": [],
      "flags": {
        "roleOnCase": null,
        "partyName": null,
        "groupId": null,
        "visibility": null,
        "details": []
      }
    },
    "specRespondent1Represented": "Yes",
    "respondent1OrgRegistered": "Yes",
    "respondent1OrganisationPolicy": {
      "OrgPolicyCaseAssignedRole": "[RESPONDENTSOLICITORONE]",
      "OrgPolicyReference": "asasas",
      "Organisation": {
        "OrganisationID": "MEVCCQF",
        "OrganisationName": "Civil Damages Claims - Organisation 2"
      },
      "PreviousOrganisations": []
    },
    "respondentSolicitor1EmailAddress": "civilmoneyclaimsdemo@gmail.com",
    "specRespondentCorrespondenceAddressRequired": "No",
    "addRespondent2": "No",
    "isFlightDelayClaim": "No",
    "detailsOfClaim": "asasasasas",
    "specClaimTimelineList": "MANUAL",
    "timelineOfEvents": [
      {
        "value": {
          "timelineDate": "2024-01-01",
          "timelineDescription": "asasasasasa"
        },
        "id": "c81d44cb-c4b5-4671-a463-01ab66f6c97f"
      }
    ],
    "speclistYourEvidenceList": [
      {
        "value": {
          "evidenceType": "CONTRACTS_AND_AGREEMENTS",
          "contractAndAgreementsEvidence": "sasasasas",
          "expertWitnessEvidence": null,
          "lettersEmailsAndOtherCorrespondenceEvidence": null,
          "photoEvidence": null,
          "receiptsEvidence": null,
          "statementOfTruthEvidence": null,
          "otherEvidence": null
        },
        "id": "46fd42b3-04af-4945-bde5-a878b6a0727c"
      }
    ],
    "claimAmountBreakup": [
      {
        "value": {
          "claimReason": "asasasa",
          "claimAmount": "300000"
        },
        "id": "ebc2b919-1464-4917-9d00-8f65f8918b29"
      }
    ],
    "claimAmountBreakupSummaryObject": "| Description | Amount | \n |---|---| \n | asasasa | £ 3000.00 |\n  | **Total** | £ 3000.00 |",
    "totalClaimAmount": "3000",
    "totalInterest": null,
    "CaseAccessCategory": null
  },
  "event_token": "#{event_token}",
  "ignore_warning": false
}